LICENSE
MANIFEST.in
README.md
setup.py
django_etesync_journal.egg-info/PKG-INFO
django_etesync_journal.egg-info/SOURCES.txt
django_etesync_journal.egg-info/dependency_links.txt
django_etesync_journal.egg-info/top_level.txt
journal/__init__.py
journal/admin.py
journal/app_settings.py
journal/apps.py
journal/models.py
journal/paginators.py
journal/permissions.py
journal/serializers.py
journal/views.py
journal/migrations/0001_initial.py
journal/migrations/0002_auto_20170217_1616.py
journal/migrations/0003_journal_version.py
journal/migrations/0004_journal_modified.py
journal/migrations/0005_userinfo.py
journal/migrations/0006_auto_20170407_1304.py
journal/migrations/0007_auto_20170407_1325.py
journal/migrations/0008_remove_userinfo_deleted.py
journal/migrations/0009_auto_20190211_1515.py
journal/migrations/0010_journalmember_readonly.py
journal/migrations/__init__.py
tests/__init__.py
tests/test_settings.py
tests/test_urls.py
tests/tests.py