Metadata-Version: 2.1
Name: django-etesync-journal
Version: 1.2.0
Summary: The server side implementation of the EteSync protocol.
Home-page: https://www.etesync.com/
Author: EteSync
Author-email: development@etesync.com
License: AGPL-3.0-only
Platform: UNKNOWN
Classifier: Environment :: Web Environment
Classifier: Framework :: Django
Classifier: Intended Audience :: Developers
Classifier: License :: OSI Approved :: GNU Affero General Public License v3
Classifier: Operating System :: OS Independent
Classifier: Programming Language :: Python
Classifier: Programming Language :: Python :: 3
Classifier: Topic :: Internet :: WWW/HTTP
Classifier: Topic :: Internet :: WWW/HTTP :: Dynamic Content
